amundsen_common/__init__.py
amundsen_common/py.typed
amundsen_common/log/__init__.py
amundsen_common/log/action_log.py
amundsen_common/log/action_log_callback.py
amundsen_common/log/action_log_model.py
amundsen_common/log/auth_caller_retrieval.py
amundsen_common/log/caller_retrieval.py
amundsen_common/log/http_header_caller_retrieval.py
amundsen_common/models/__init__.py
amundsen_common/models/dashboard.py
amundsen_common/models/index_map.py
amundsen_common/models/popular_table.py
amundsen_common/models/table.py
amundsen_common/models/user.py
amundsencommon_azure-0.3.9.dist-info/LICENSE
amundsencommon_azure-0.3.9.dist-info/METADATA
amundsencommon_azure-0.3.9.dist-info/NOTICE
amundsencommon_azure-0.3.9.dist-info/WHEEL
amundsencommon_azure-0.3.9.dist-info/top_level.txt
amundsencommon_azure-0.3.9.dist-info/RECORD
