Metadata-Version: 2.1
Name: amundsencommon-azure
Version: 0.3.9
Summary: Common code library for Amundsen
Home-page: https://github.com/kylg/amundsencommon
Maintainer: kylg
Maintainer-email: info@kylg.org
License: UNKNOWN
Platform: UNKNOWN
Requires-Python: >=3.6
Requires-Dist: flask (>=1.0.2)
